ripiu/cmsplugin_iubenda/__init__.py
ripiu/cmsplugin_iubenda/apps.py
ripiu/cmsplugin_iubenda/cms_plugins.py
ripiu/cmsplugin_iubenda/models.py
ripiu/cmsplugin_iubenda/locale/.DS_Store
ripiu/cmsplugin_iubenda/locale/it/.DS_Store
ripiu/cmsplugin_iubenda/locale/it/LC_MESSAGES/django.mo
ripiu/cmsplugin_iubenda/locale/it/LC_MESSAGES/django.po
ripiu/cmsplugin_iubenda/migrations/0001_initial.py
ripiu/cmsplugin_iubenda/migrations/__init__.py
ripiu/cmsplugin_iubenda/migrations/__pycache__/__init__.cpython-36.pyc
ripiu/cmsplugin_iubenda/templates/.DS_Store
ripiu/cmsplugin_iubenda/templates/ripiu/.DS_Store
ripiu/cmsplugin_iubenda/templates/ripiu/cmsplugin_iubenda/button.html
ripiu.cmsplugin_iubenda-0.0.3.dist-info/DESCRIPTION.rst
ripiu.cmsplugin_iubenda-0.0.3.dist-info/METADATA
ripiu.cmsplugin_iubenda-0.0.3.dist-info/RECORD
ripiu.cmsplugin_iubenda-0.0.3.dist-info/WHEEL
ripiu.cmsplugin_iubenda-0.0.3.dist-info/metadata.json
ripiu.cmsplugin_iubenda-0.0.3.dist-info/top_level.txt
