Metadata-Version: 2.0
Name: ripiu.cmsplugin-iubenda
Version: 0.0.3
Summary: Django CMS Iubenda integration
Home-page: https://github.com/ripiu/ripiu.cmsplugin_iubenda
Author: matteo vezzola
Author-email: matteo@studioripiu.it
License: BSD-new
Platform: UNKNOWN
Classifier: Development Status :: 3 - Alpha
Classifier: Framework :: Django
Classifier: Intended Audience :: Developers
Classifier: License :: OSI Approved :: BSD License
Classifier: Operating System :: OS Independent
Classifier: Programming Language :: Python
Classifier: Topic :: Internet :: WWW/HTTP :: Dynamic Content
Requires-Python: >=3.3
Requires-Dist: Django (>=1.8)
Requires-Dist: django-cms (>=3.1)
